{"install_options":{"debug":false,"strict":false,"force":false},"source":{"raw":{"id":"pkg:github/johnnymorganz/stylua@v2.3.1","asset":[{"file":"stylua-macos-aarch64.zip","target":"darwin_arm64","bin":"stylua"},{"file":"stylua-macos-x86_64.zip","target":"darwin_x64","bin":"stylua"},{"file":"stylua-linux-x86_64.zip","target":"linux_x64_gnu","bin":"stylua"},{"file":"stylua-linux-aarch64.zip","target":"linux_arm64_gnu","bin":"stylua"},{"file":"stylua-linux-x86_64-musl.zip","target":"linux_x64","bin":"stylua"},{"file":"stylua-windows-x86_64.zip","target":"win_x64","bin":"stylua.exe"}]},"id":"pkg:github/johnnymorganz/stylua@v2.3.1","type":"registry+v1"},"schema_version":"2.0","name":"stylua","registry":{"version":"2026-01-12-upbeat-ram","checksums":{"registry.json":"08e512b2cf7d2384c693372394f1a141df1a7c9b6d1d12f32095d1392c329212","registry.json.zip":"07b98d9a1b4027e7068acd45ce139a495a5bd570a9b6942961045e4d2b56bf46"},"name":"mason-registry","proto":"github","namespace":"mason-org"},"links":{"opt":{},"bin":{"stylua":"stylua"},"share":{}},"metrics":{"completion_time":1768255785295,"start_time":1768255784420}}